django_prototyper-0.1.21.dist-info/METADATA
django_prototyper-0.1.21.dist-info/RECORD
django_prototyper-0.1.21.dist-info/WHEEL
django_prototyper-0.1.21.dist-info/entry_points.txt
django_prototyper-0.1.21.dist-info/top_level.txt
prototyper/__init__.py
prototyper/cli.py
prototyper/conf.py
prototyper/server.py
prototyper/urls.py
prototyper/version.py
prototyper/views.py
prototyper/build/__init__.py
prototyper/build/base.py
prototyper/build/log.py
prototyper/build/main.py
prototyper/build/stages/__init__.py
prototyper/build/stages/admin.py
prototyper/build/stages/core.py
prototyper/build/stages/models.py
prototyper/build/stages/requirements.py
prototyper/build/stages/settings.py
prototyper/build/stages/urls.py
prototyper/build/stages/wsgi_app.py
prototyper/demo_plugins/codeon-docker/config.json
prototyper/demo_plugins/codeon-docker/plugin.py
prototyper/demo_plugins/codeon-docker/templates/main.py
prototyper/demo_plugins/codeon-docker/templates/{{proj_name}}/settings_staging.py
prototyper/demo_plugins/codeon-docker/templates/{{proj_name}}/fixtures/staging_admin.json
prototyper/demo_plugins/codeon-staging/config.json
prototyper/demo_plugins/django-compressor/config.json
prototyper/demo_plugins/django-debug-toolbar/config.json
prototyper/demo_plugins/django-mptt/config.json
prototyper/demo_plugins/django-rest-framework/config.json
prototyper/demo_plugins/dummy/config.json
prototyper/demo_plugins/graphene-django/config.json
prototyper/demo_plugins/pydummy/config.json
prototyper/demo_plugins/pydummy/plugin.py
prototyper/plugins/__init__.py
prototyper/plugins/base.py
prototyper/plugins/discover.py
prototyper/plugins/install.py
prototyper/plugins/loading.py
prototyper/plugins/template.py
prototyper/project/__init__.py
prototyper/project/initial.py
prototyper/project/store.py
prototyper/static/build.js
prototyper/static/logo.png
prototyper/static/welcome.png
prototyper/utils/__init__.py
prototyper/utils/inspection/__init__.py
prototyper/utils/inspection/apps.py
prototyper/utils/inspection/field.py
prototyper/utils/inspection/main.py
prototyper/utils/inspection/model.py
